easysave/__init__.py
easysave/easysave.py
easysave/ezsave.py
ezsave/__init__.py
ezsave/ezsave.py
easysave-0.1.0.5.dist-info/METADATA
easysave-0.1.0.5.dist-info/WHEEL
easysave-0.1.0.5.dist-info/top_level.txt
easysave-0.1.0.5.dist-info/RECORD
