Metadata-Version: 2.1
Name: easysave
Version: 0.1.0.5
Summary: data saving library
Home-page: https://github.com/tbubhnh/ez_save/
Author: tbubhnh
Author-email: tbubhnh11112@gmail.com
License: MIT
Classifier: Intended Audience :: Developers
Classifier: License :: OSI Approved :: MIT License
Classifier: Programming Language :: Python
Classifier: Programming Language :: Python :: 3
Classifier: Programming Language :: Python :: 3.6
Classifier: Programming Language :: Python :: 3.7
Classifier: Programming Language :: Python :: 3.8
Classifier: Programming Language :: Python :: 3.9
Classifier: Operating System :: OS Independent
Requires-Dist: cryptocode
